{
    "jogos": [
        {
            "data": "19/05/2025",
            "time1": "FURIA",
            "time2": "The MongolZ",
            "link": "https://www.hltv.org/matches/2382377/the-mongolz-vs-furia-iem-dallas-2025",
            "thread_id": 306
        },
        {
            "data": "07/06/2025",
            "time1": "FURIA",
            "time2": "Time 2",
            "link": "https://www.hltv.org/matches/2382430/furia-vs-tbd-blasttv-austin-major-2025-stage-2",
            "thread_id": 314
        },
        {
            "data": "10/05/2025",
            "time1": "FURIA",
            "time2": "GamerLegion",
            "link": "https://www.hltv.org/matches/2382222/gamerlegion-vs-furia-pgl-astana-2025",
            "thread_id": 328
        }
    ]
}